rlbtf/__init__.py
rlbtf-0.1.0.dist-info/LICENSE
rlbtf-0.1.0.dist-info/WHEEL
rlbtf-0.1.0.dist-info/METADATA
rlbtf-0.1.0.dist-info/RECORD
